{
    "Version": "1.2",
    "Data": {
        "Source": "l:\\unreal projects\\slashworld 5.3\\intermediate\\build\\win64\\unrealeditor\\inc\\slashworld\\uht\\slashworld.init.gen.cpp",
        "ProvidedModule": "",
        "PCH": "l:\\unreal projects\\slashworld 5.3\\intermediate\\build\\win64\\x64\\unrealeditor\\development\\engine\\sharedpch.engine.cpp20.h.pch",
        "Includes": [
            "l:\\unreal projects\\slashworld 5.3\\intermediate\\build\\win64\\x64\\unrealeditor\\development\\slashworld\\definitions.slashworld.h"
        ],
        "ImportedModules": [],
        "ImportedHeaderUnits": []
    }
}